config_fetcher/__init__.py
config_fetcher-1.0.2.dist-info/METADATA
config_fetcher-1.0.2.dist-info/WHEEL
config_fetcher-1.0.2.dist-info/licenses/LICENSE
config_fetcher-1.0.2.dist-info/RECORD
